treefeeder/__init__.py
treefeeder/parser.py
treefeeder-0.0.7.data/scripts/treefeeder
treefeeder-0.0.7.dist-info/LICENSE
treefeeder-0.0.7.dist-info/METADATA
treefeeder-0.0.7.dist-info/WHEEL
treefeeder-0.0.7.dist-info/top_level.txt
treefeeder-0.0.7.dist-info/RECORD
