Metadata-Version: 2.1
Name: treefeeder
Version: 0.0.7
Summary: Feed the contents of a folder into your ChatGPT/LLM queries faster
Author-email: Anton Potapov <fgreyeducation@gmail.com>
License: MIT License
License-File: LICENSE
